aiessentials/__init__.py
aiessentials-0.0.0.dist-info/METADATA
aiessentials-0.0.0.dist-info/WHEEL
aiessentials-0.0.0.dist-info/top_level.txt
aiessentials-0.0.0.dist-info/RECORD
